add_hamiltonian.py
architectures.py
bootstrap_estimator.py
hamiltonian_parser.py
measurement_simulator.py
performance_estimator.py
policy_engine.py
symqnet_cli.py
universal_wrapper.py
utils.py
symqnet_molopt-3.0.21.data/data/examples/BeH2_10q.json
symqnet_molopt-3.0.21.data/data/models/FINAL_FIXED_SYMQNET.pth
symqnet_molopt-3.0.21.data/data/models/vae_M10_f.pth
symqnet_molopt-3.0.21.dist-info/licenses/LICENSE
symqnet_molopt-3.0.21.dist-info/METADATA
symqnet_molopt-3.0.21.dist-info/WHEEL
symqnet_molopt-3.0.21.dist-info/entry_points.txt
symqnet_molopt-3.0.21.dist-info/top_level.txt
symqnet_molopt-3.0.21.dist-info/RECORD
