Metadata-Version: 2.4
Name: symqnet-molopt
Version: 3.0.21
Summary: SymQNet Molecular Optimization via Hamiltonian Estimation
Home-page: https://github.com/YTomar79/symqnet-molopt
Author: YTomar79
Author-email: yashm.tomar@gmail.com
License: MIT
Classifier: Development Status :: 5 - Production/Stable
Classifier: Intended Audience :: Science/Research
Classifier: Topic :: Scientific/Engineering :: Physics
Classifier: License :: OSI Approved :: MIT License
Classifier: Programming Language :: Python :: 3
Classifier: Operating System :: OS Independent
Classifier: Environment :: Console
Requires-Python: >=3.8
License-File: LICENSE
Requires-Dist: torch<3.0.0,>=2.8.0
Requires-Dist: numpy<3.0.0,>=2.3.3
Requires-Dist: qiskit<3.0.0,>=2.1.2
Requires-Dist: openfermion>=1.7.0
Requires-Dist: scipy<2.0.0,>=1.16.2
Requires-Dist: click<9.0.0,>=8.3.0
Requires-Dist: tqdm<5.0.0,>=4.67.1
Requires-Dist: matplotlib<4.0.0,>=3.10.6
Requires-Dist: seaborn<1.0.0,>=0.11.2
Requires-Dist: torch-geometric<3.0.0,>=2.3.0
Requires-Dist: pandas<3.0.0,>=2.0.0
Requires-Dist: tensorboard<3.0.0,>=2.13.0
Requires-Dist: gymnasium<2.0.0,>=1.2.0
Provides-Extra: dev
Requires-Dist: pytest>=6.0; extra == "dev"
Requires-Dist: pytest-cov>=2.0; extra == "dev"
Requires-Dist: black>=22.0; extra == "dev"
Requires-Dist: flake8>=4.0; extra == "dev"
Requires-Dist: isort>=5.0; extra == "dev"
Requires-Dist: mypy>=0.950; extra == "dev"
Provides-Extra: docs
Requires-Dist: sphinx>=4.0; extra == "docs"
Requires-Dist: sphinx-rtd-theme>=1.0; extra == "docs"
Requires-Dist: myst-parser>=0.17; extra == "docs"
Provides-Extra: gpu
Requires-Dist: torch>=1.12.0; extra == "gpu"
Requires-Dist: torch-geometric>=2.2.0; extra == "gpu"
Provides-Extra: analysis
Requires-Dist: pandas>=1.4.0; extra == "analysis"
Requires-Dist: seaborn>=0.11.0; extra == "analysis"
Requires-Dist: scikit-learn>=1.1.0; extra == "analysis"
Dynamic: author
Dynamic: author-email
Dynamic: classifier
Dynamic: description
Dynamic: description-content-type
Dynamic: home-page
Dynamic: license
Dynamic: license-file
Dynamic: provides-extra
Dynamic: requires-dist
Dynamic: requires-python
Dynamic: summary
